synapgrad/__init__.py
synapgrad/conv_tools.py
synapgrad/cpu_ops.py
synapgrad/device.py
synapgrad/functional.py
synapgrad/tensor.py
synapgrad/utils.py
synapgrad/nn/__init__.py
synapgrad/nn/activations.py
synapgrad/nn/functional.py
synapgrad/nn/init.py
synapgrad/nn/layers.py
synapgrad/nn/losses.py
synapgrad/nn/modules.py
synapgrad/nn/utils/__init__.py
synapgrad/nn/utils/data.py
synapgrad/nn/utils/train.py
synapgrad/optim/__init__.py
synapgrad/optim/optimizers.py
synapgrad/visual/__init__.py
synapgrad/visual/graph.py
synapgrad-1.0.2.dist-info/LICENSE
synapgrad-1.0.2.dist-info/METADATA
synapgrad-1.0.2.dist-info/WHEEL
synapgrad-1.0.2.dist-info/top_level.txt
synapgrad-1.0.2.dist-info/RECORD
