Metadata-Version: 2.1
Name: synapgrad
Version: 1.0.2
Summary: A lightweight autograd engine with a deep learning library and a Torch-like API
Author-email: Pablo García Mesa <pgmesa.sm@gmail.com>
License: MIT
Project-URL: Homepage, https://github.com/pgmesa/synapgrad
Keywords: Autograd,Tensor,Machine Learning,Deep Learning,Python
Classifier: Development Status :: 5 - Production/Stable
Classifier: Intended Audience :: Developers
Classifier: Intended Audience :: Education
Classifier: Intended Audience :: Science/Research
Classifier: License :: OSI Approved :: MIT License
Classifier: Operating System :: OS Independent
Classifier: Programming Language :: Python :: 3
Classifier: Programming Language :: Python :: 3.9
Classifier: Programming Language :: Python :: 3.10
Classifier: Programming Language :: Python :: 3.11
Classifier: Programming Language :: Python :: 3.12
Classifier: Topic :: Scientific/Engineering
Classifier: Topic :: Scientific/Engineering :: Mathematics
Classifier: Topic :: Scientific/Engineering :: Artificial Intelligence
Classifier: Topic :: Software Development
Classifier: Topic :: Software Development :: Libraries
Classifier: Topic :: Software Development :: Libraries :: Python Modules
Requires-Python: >=3.9
License-File: LICENSE
Requires-Dist: numpy<3.0.0,>=1.23.0
Provides-Extra: train
Requires-Dist: pkbar==0.5; extra == "train"
Requires-Dist: matplotlib<4.0.0,>=3.0.0; extra == "train"
Requires-Dist: scikit-learn<2.0.0,>=1.2.1; extra == "train"
